[
    {
        "key": "group_57d715079ac4a",
        "title": "Произволный заголовок",
        "fields": [
            {
                "key": "field_57d7150b68513",
                "label": "Произвольный H1",
                "name": "custom_h1",
                "type": "textarea",
                "instructions": "",
                "required": 0,
                "conditional_logic": 0,
                "wrapper": {
                    "width": "100",
                    "class": "",
                    "id": ""
                },
                "default_value": "",
                "placeholder": "",
                "maxlength": "",
                "rows": 2,
                "new_lines": "br"
            }
        ],
        "location": [
            [
                {
                    "param": "post_type",
                    "operator": "==",
                    "value": "post"
                }
            ],
            [
                {
                    "param": "post_type",
                    "operator": "==",
                    "value": "page"
                },
                {
                    "param": "page_type",
                    "operator": "!=",
                    "value": "front_page"
                }
            ],
            [
                {
                    "param": "taxonomy",
                    "operator": "==",
                    "value": "all"
                }
            ]
        ],
        "menu_order": -5,
        "position": "acf_after_title",
        "style": "default",
        "label_placement": "top",
        "instruction_placement": "label",
        "hide_on_screen": "",
        "active": true,
        "description": ""
    },
    {
        "key": "group_5d189f5240772",
        "title": "Наполнение",
        "fields": [],
        "location": [
            [
                {
                    "param": "post_type",
                    "operator": "==",
                    "value": "post"
                }
            ]
        ],
        "menu_order": 0,
        "position": "acf_after_title",
        "style": "default",
        "label_placement": "top",
        "instruction_placement": "label",
        "hide_on_screen": "",
        "active": true,
        "description": ""
    },
    {
        "key": "group_57d8081728644",
        "title": "Компановщик страницы",
        "fields": [
            {
                "key": "field_57d80835f8983",
                "label": "Компановщик",
                "name": "page_builder",
                "type": "flexible_content",
                "instructions": "",
                "required": 0,
                "conditional_logic": 0,
                "wrapper": {
                    "width": "",
                    "class": "",
                    "id": ""
                },
                "layouts": {
                    "57d9c30d8dc3f": {
                        "key": "57d9c30d8dc3f",
                        "name": "module-text",
                        "label": "Текстовый блок",
                        "display": "block",
                        "sub_fields": [
                            {
                                "key": "field_57d9c3878dc40",
                                "label": "Количество колонок",
                                "name": "col",
                                "type": "select",
                                "instructions": "",
                                "required": 1,
                                "conditional_logic": 0,
                                "wrapper": {
                                    "width": "100",
                                    "class": "",
                                    "id": ""
                                },
                                "choices": {
                                    "1": "Одна",
                                    "2": "Две",
                                    "3": "Три",
                                    "4": "Четыре"
                                },
                                "default_value": [
                                    1
                                ],
                                "allow_null": 0,
                                "multiple": 0,
                                "ui": 0,
                                "return_format": "value",
                                "ajax": 0,
                                "placeholder": ""
                            },
                            {
                                "key": "field_5cf52dfcf6310",
                                "label": "Содержимое",
                                "name": "text_col_1",
                                "type": "wysiwyg",
                                "instructions": "",
                                "required": 0,
                                "conditional_logic": [
                                    [
                                        {
                                            "field": "field_57d9c3878dc40",
                                            "operator": "==",
                                            "value": "1"
                                        }
                                    ]
                                ],
                                "wrapper": {
                                    "width": "100",
                                    "class": "",
                                    "id": ""
                                },
                                "default_value": "",
                                "tabs": "all",
                                "toolbar": "full",
                                "media_upload": 1,
                                "delay": 0
                            },
                            {
                                "key": "field_5cf52e3cf6312",
                                "label": "Колонка [1]",
                                "name": "text_col_1",
                                "type": "wysiwyg",
                                "instructions": "",
                                "required": 1,
                                "conditional_logic": [
                                    [
                                        {
                                            "field": "field_57d9c3878dc40",
                                            "operator": "==",
                                            "value": "2"
                                        }
                                    ]
                                ],
                                "wrapper": {
                                    "width": "50",
                                    "class": "",
                                    "id": ""
                                },
                                "default_value": "",
                                "tabs": "all",
                                "toolbar": "full",
                                "media_upload": 1,
                                "delay": 0
                            },
                            {
                                "key": "field_5cf52e32f6311",
                                "label": "Колонка [2]",
                                "name": "text_col_2",
                                "type": "wysiwyg",
                                "instructions": "",
                                "required": 1,
                                "conditional_logic": [
                                    [
                                        {
                                            "field": "field_57d9c3878dc40",
                                            "operator": "==",
                                            "value": "2"
                                        }
                                    ]
                                ],
                                "wrapper": {
                                    "width": "50",
                                    "class": "",
                                    "id": ""
                                },
                                "default_value": "",
                                "tabs": "all",
                                "toolbar": "full",
                                "media_upload": 1,
                                "delay": 0
                            },
                            {
                                "key": "field_5cf52e63f6313",
                                "label": "Колонка [1]",
                                "name": "text_col_1",
                                "type": "wysiwyg",
                                "instructions": "",
                                "required": 1,
                                "conditional_logic": [
                                    [
                                        {
                                            "field": "field_57d9c3878dc40",
                                            "operator": "==",
                                            "value": "3"
                                        }
                                    ]
                                ],
                                "wrapper": {
                                    "width": "33.333333",
                                    "class": "",
                                    "id": ""
                                },
                                "default_value": "",
                                "tabs": "all",
                                "toolbar": "full",
                                "media_upload": 1,
                                "delay": 0
                            },
                            {
                                "key": "field_5cf52e71f6314",
                                "label": "Колонка [2]",
                                "name": "text_col_2",
                                "type": "wysiwyg",
                                "instructions": "",
                                "required": 1,
                                "conditional_logic": [
                                    [
                                        {
                                            "field": "field_57d9c3878dc40",
                                            "operator": "==",
                                            "value": "3"
                                        }
                                    ]
                                ],
                                "wrapper": {
                                    "width": "33.333333",
                                    "class": "",
                                    "id": ""
                                },
                                "default_value": "",
                                "tabs": "all",
                                "toolbar": "full",
                                "media_upload": 1,
                                "delay": 0
                            },
                            {
                                "key": "field_5cf52e7af6315",
                                "label": "Колонка [3]",
                                "name": "text_col_3",
                                "type": "wysiwyg",
                                "instructions": "",
                                "required": 0,
                                "conditional_logic": [
                                    [
                                        {
                                            "field": "field_57d9c3878dc40",
                                            "operator": "==",
                                            "value": "3"
                                        }
                                    ]
                                ],
                                "wrapper": {
                                    "width": "33.333333",
                                    "class": "",
                                    "id": ""
                                },
                                "default_value": "",
                                "tabs": "all",
                                "toolbar": "full",
                                "media_upload": 1,
                                "delay": 0
                            },
                            {
                                "key": "field_57d9c3b98dc41",
                                "label": "Колонка [1]",
                                "name": "text_col_1",
                                "type": "wysiwyg",
                                "instructions": "",
                                "required": 1,
                                "conditional_logic": [
                                    [
                                        {
                                            "field": "field_57d9c3878dc40",
                                            "operator": "==",
                                            "value": "4"
                                        }
                                    ]
                                ],
                                "wrapper": {
                                    "width": "25",
                                    "class": "",
                                    "id": ""
                                },
                                "default_value": "",
                                "tabs": "all",
                                "toolbar": "full",
                                "media_upload": 1,
                                "delay": 0
                            },
                            {
                                "key": "field_57d9c4048dc45",
                                "label": "Колонка [2]",
                                "name": "text_col_2",
                                "type": "wysiwyg",
                                "instructions": "",
                                "required": 0,
                                "conditional_logic": [
                                    [
                                        {
                                            "field": "field_57d9c3878dc40",
                                            "operator": "==",
                                            "value": "4"
                                        }
                                    ]
                                ],
                                "wrapper": {
                                    "width": "25",
                                    "class": "",
                                    "id": ""
                                },
                                "default_value": "",
                                "tabs": "all",
                                "toolbar": "full",
                                "media_upload": 1,
                                "delay": 0
                            },
                            {
                                "key": "field_57d9c4318dc46",
                                "label": "Колонка [3]",
                                "name": "text_col_3",
                                "type": "wysiwyg",
                                "instructions": "",
                                "required": 0,
                                "conditional_logic": [
                                    [
                                        {
                                            "field": "field_57d9c3878dc40",
                                            "operator": "==",
                                            "value": "4"
                                        }
                                    ]
                                ],
                                "wrapper": {
                                    "width": "25",
                                    "class": "",
                                    "id": ""
                                },
                                "default_value": "",
                                "tabs": "all",
                                "toolbar": "full",
                                "media_upload": 1,
                                "delay": 0
                            },
                            {
                                "key": "field_57d9c43a8dc47",
                                "label": "Колонка [4]",
                                "name": "text_col_4",
                                "type": "wysiwyg",
                                "instructions": "",
                                "required": 0,
                                "conditional_logic": [
                                    [
                                        {
                                            "field": "field_57d9c3878dc40",
                                            "operator": "==",
                                            "value": "4"
                                        }
                                    ]
                                ],
                                "wrapper": {
                                    "width": "25",
                                    "class": "",
                                    "id": ""
                                },
                                "default_value": "",
                                "tabs": "all",
                                "toolbar": "full",
                                "media_upload": 1,
                                "delay": 0
                            },
                            {
                                "key": "field_5cf52da4f630f",
                                "label": "Узкий контент",
                                "name": "narrow-content",
                                "type": "true_false",
                                "instructions": "",
                                "required": 0,
                                "conditional_logic": 0,
                                "wrapper": {
                                    "width": "",
                                    "class": "",
                                    "id": ""
                                },
                                "message": "Текст не на всю ширину блока",
                                "default_value": 1,
                                "ui": 0,
                                "ui_on_text": "",
                                "ui_off_text": ""
                            }
                        ],
                        "min": "",
                        "max": ""
                    }
                },
                "button_label": "Добавить модуль",
                "min": "",
                "max": ""
            }
        ],
        "location": [
            [
                {
                    "param": "post_type",
                    "operator": "==",
                    "value": "page"
                },
                {
                    "param": "page_template",
                    "operator": "!=",
                    "value": "default"
                }
            ],
            [
                {
                    "param": "post_type",
                    "operator": "==",
                    "value": "post"
                }
            ]
        ],
        "menu_order": 20,
        "position": "acf_after_title",
        "style": "default",
        "label_placement": "top",
        "instruction_placement": "label",
        "hide_on_screen": "",
        "active": true,
        "description": ""
    }
]